trilla_lib/__init__.py
trilla_lib/aiohttp.py
trilla_lib/contextvars.py
trilla_lib/httpx.py
trilla_lib/infra/__init__.py
trilla_lib/infra/cassandra/__init__.py
trilla_lib/infra/cassandra/config.py
trilla_lib/infra/cassandra/deps.py
trilla_lib/infra/centrifugo/__init__.py
trilla_lib/infra/centrifugo/config.py
trilla_lib/infra/centrifugo/deps.py
trilla_lib/infra/chat/__init__.py
trilla_lib/infra/chat/config.py
trilla_lib/infra/db/__init__.py
trilla_lib/infra/db/config.py
trilla_lib/infra/db/deps.py
trilla_lib/infra/debezium/__init__.py
trilla_lib/infra/debezium/config.py
trilla_lib/infra/debezium/deps.py
trilla_lib/infra/feed/__init__.py
trilla_lib/infra/feed/config.py
trilla_lib/infra/feed/deps.py
trilla_lib/infra/jaeger/__init__.py
trilla_lib/infra/jaeger/config.py
trilla_lib/infra/jaeger/tracing.py
trilla_lib/infra/kafka/__init__.py
trilla_lib/infra/kafka/config.py
trilla_lib/infra/kafka/deps.py
trilla_lib/infra/location/__init__.py
trilla_lib/infra/location/config.py
trilla_lib/infra/location/deps.py
trilla_lib/infra/main/__init__.py
trilla_lib/infra/main/config.py
trilla_lib/infra/main/deps.py
trilla_lib/infra/media/__init__.py
trilla_lib/infra/media/config.py
trilla_lib/infra/media/deps.py
trilla_lib/infra/minio/__init__.py
trilla_lib/infra/minio/config.py
trilla_lib/infra/minio/deps.py
trilla_lib/infra/online/__init__.py
trilla_lib/infra/online/config.py
trilla_lib/infra/online/deps.py
trilla_lib/infra/redis/__init__.py
trilla_lib/infra/redis/config.py
trilla_lib/infra/redis/deps.py
trilla_lib/infra/reel/__init__.py
trilla_lib/infra/reel/config.py
trilla_lib/infra/reel/deps.py
trilla_lib/infra/sentry/__init__.py
trilla_lib/infra/sentry/integration.py
trilla_lib/infra/sentry/settings.py
trilla_lib/logging.py
trilla_lib/middleware/__init__.py
trilla_lib/middleware/context.py
trilla_lib/svc/__init__.py
trilla_lib/svc/jwt/__init__.py
trilla_lib/svc/jwt/config.py
trilla_lib/svc/jwt/deps.py
trilla_lib-0.1.109.dist-info/METADATA
trilla_lib-0.1.109.dist-info/WHEEL
trilla_lib-0.1.109.dist-info/RECORD
