Metadata-Version: 2.1
Name: trilla-lib
Version: 0.1.109
Summary: 
License: 0.1.0
Author: Артур Лагунов
Author-email: lagunovartur@inbox.ru
Requires-Python: >=3.10,<4.0
Classifier: License :: Other/Proprietary License
Classifier: Programming Language :: Python :: 3
Classifier: Programming Language :: Python :: 3.10
Classifier: Programming Language :: Python :: 3.11
Classifier: Programming Language :: Python :: 3.12
Requires-Dist: deprecated (>=1.2.18,<2.0.0)
Requires-Dist: grpcio (==1.63.0)
Requires-Dist: opentelemetry-api (>=1.33.0,<2.0.0)
Requires-Dist: opentelemetry-exporter-jaeger (>=1.21.0,<2.0.0)
Requires-Dist: opentelemetry-instrumentation-aiohttp-client (>=0.55b1,<0.56)
Requires-Dist: opentelemetry-instrumentation-aiokafka (>=0.55b1,<0.56)
Requires-Dist: opentelemetry-instrumentation-asgi (>=0.55b,<0.56)
Requires-Dist: opentelemetry-instrumentation-fastapi (>=0.55b,<0.56)
Requires-Dist: opentelemetry-instrumentation-httpx (>=0.55b,<0.56)
Requires-Dist: opentelemetry-instrumentation-logging (>=0.55b0,<0.56)
Requires-Dist: opentelemetry-instrumentation-redis (>=0.55b,<0.56)
Requires-Dist: opentelemetry-instrumentation-sqlalchemy (>=0.55b,<0.56)
Requires-Dist: opentelemetry-sdk (>=1.33.0,<2.0.0)
Requires-Dist: pydantic (>=1.10.0,<2.0.0)
Requires-Dist: python-json-logger (>=3.3.0,<4.0.0)
Requires-Dist: redis (>=6.2.0,<7.0.0)
Requires-Dist: sentry-sdk[opentelemetry] (>=2.29.1,<3.0.0)
Requires-Dist: yarl (>=1.20.1,<2.0.0)
